scripting_tools/__init__.py
scripting_tools/argsguard.py
scripting_tools/colorama_ext.py
scripting_tools/generator.py
scripting_tools/hash.py
scripting_tools/log.py
scripting_tools/ostools.py
scripting_tools/parse.py
scripting_tools/progression_bar.py
scripting_tools/sysargs.py
scripting_tools-0.1.1.dist-info/LICENSE
scripting_tools-0.1.1.dist-info/METADATA
scripting_tools-0.1.1.dist-info/WHEEL
scripting_tools-0.1.1.dist-info/top_level.txt
scripting_tools-0.1.1.dist-info/RECORD
